temba_client/__init__.py
temba_client/base.py
temba_client/exceptions.py
temba_client/serialization.py
temba_client/tests.py
temba_client/utils.py
temba_client/v2/__init__.py
temba_client/v2/tests.py
temba_client/v2/types.py
rapidpro_python-2.22.0.dist-info/METADATA
rapidpro_python-2.22.0.dist-info/WHEEL
rapidpro_python-2.22.0.dist-info/licenses/LICENSE
rapidpro_python-2.22.0.dist-info/RECORD
