Metadata-Version: 2.4
Name: rapidpro-python
Version: 2.22.0
Summary: Python client library for the RapidPro API
Project-URL: Repository, http://github.com/rapidpro/rapidpro-python
Author-email: Nyaruka <code@nyaruka.com>
License: BSD-4-Clause
License-File: LICENSE
Classifier: Development Status :: 5 - Production/Stable
Classifier: Intended Audience :: Developers
Classifier: License :: OSI Approved :: BSD License
Classifier: Programming Language :: Python :: 3
Classifier: Topic :: Software Development :: Libraries
Requires-Python: >=3.12
Requires-Dist: iso8601>=0.1.13
Requires-Dist: requests>=2.32.0
